oyou/__init__.py
oyou-0.2.1.dist-info/DESCRIPTION.rst
oyou-0.2.1.dist-info/METADATA
oyou-0.2.1.dist-info/RECORD
oyou-0.2.1.dist-info/WHEEL
oyou-0.2.1.dist-info/metadata.json
oyou-0.2.1.dist-info/top_level.txt
