Metadata-Version: 2.0
Name: oyou
Version: 0.2.1
Summary: Build and make use of tensorflow model with pleasure and flexibility
Home-page: http://github.com/sepmein/oyou
Author: Spencer Zhang
Author-email: sepmein@hotmail.com
License: MIT
Keywords: tensorflow machine-learning graph-util
Platform: UNKNOWN
Classifier: Development Status :: 3 - Alpha
Classifier: Intended Audience :: Developers
Classifier: Topic :: Scientific/Engineering :: Artificial Intelligence
Classifier: License :: OSI Approved :: MIT License
Classifier: Programming Language :: Python :: 2
Classifier: Programming Language :: Python :: 2.7
Classifier: Programming Language :: Python :: 3
Classifier: Programming Language :: Python :: 3.3
Classifier: Programming Language :: Python :: 3.4
Classifier: Programming Language :: Python :: 3.5
Requires-Dist: tensorflow
Requires-Dist: numpy
